czifile/__init__.py
czifile/__main__.py
czifile/czi2tif.py
czifile/czifile.py
czifile-2019.7.2.1.dist-info/LICENSE
czifile-2019.7.2.1.dist-info/METADATA
czifile-2019.7.2.1.dist-info/WHEEL
czifile-2019.7.2.1.dist-info/entry_points.txt
czifile-2019.7.2.1.dist-info/top_level.txt
czifile-2019.7.2.1.dist-info/RECORD
